ups_lib/__init__.py
ups_lib/access_request.py
ups_lib/av_request.py
ups_lib/av_response.py
ups_lib/common.py
ups_lib/document_upload_request.py
ups_lib/document_upload_response.py
ups_lib/error_1_1.py
ups_lib/freight_pickup_web_service_schema.py
ups_lib/freight_rate_web_service_schema.py
ups_lib/freight_ship_web_service_schema.py
ups_lib/paperless_document_api.py
ups_lib/pickup_web_service_schema.py
ups_lib/rate_web_service_schema.py
ups_lib/rest_error.py
ups_lib/rest_tracking_response.py
ups_lib/ship_web_service_schema.py
ups_lib/ups_security.py
ups_lib/void_web_service_schema.py
carrier.ups-2023.3.dist-info/METADATA
carrier.ups-2023.3.dist-info/WHEEL
carrier.ups-2023.3.dist-info/top_level.txt
carrier.ups-2023.3.dist-info/RECORD
